ShortName.py
ShortName-1.1.0.dist-info/LICENSE
ShortName-1.1.0.dist-info/METADATA
ShortName-1.1.0.dist-info/WHEEL
ShortName-1.1.0.dist-info/entry_points.txt
ShortName-1.1.0.dist-info/top_level.txt
ShortName-1.1.0.dist-info/zip-safe
ShortName-1.1.0.dist-info/RECORD
