Metadata-Version: 2.1
Name: ShortName
Version: 1.1.0
Summary: Command-line utility to view and modify 8.3-style short file names on Windows
Author: Eta
License: zlib/libpng License
Project-URL: Homepage, https://github.com/Eta0/ShortName
Keywords: windows,cli
Platform: Win32 (MS Windows)
Classifier: Programming Language :: Python :: 3
Classifier: License :: OSI Approved :: zlib/libpng License
Classifier: Development Status :: 4 - Beta
Classifier: Environment :: Console
Classifier: Environment :: Win32 (MS Windows)
Classifier: Operating System :: Microsoft :: Windows
Classifier: Intended Audience :: End Users/Desktop
Requires-Python: >=3.6
License-File: LICENSE
